{
  "week_label": "2026-07-15〜2026-07-21",
  "one_liner": "週前半は石油ガス株の急伸や外国人投資家の買い越しで反発の兆しを見せたものの、週後半にはVN指数が急落し3ヶ月ぶり安値を更新、外国人の大幅な売り越しや証券各社のQ2業績悪化が市場センチメントを冷やした一週間となりました。",
  "themes": [
    {
      "title": "市場の急変動と外国人投資家の動向",
      "points": [
        "週前半は石油ガス株が急伸し、VN指数は一時反転の動きを見せた。",
        "週後半にはVN指数が44ポイント急落し、3ヶ月ぶりの安値を更新した。",
        "外国人投資家は週中に買い越しを見せたものの、週全体では2.1兆ドン超の売り越しに転じた。"
      ]
    },
    {
      "title": "企業業績の明暗と金融市場の課題",
      "points": [
        "証券各社は第2四半期利益が大幅に減少したことが報じられた。",
        "住宅ローン金利が16%を超える水準となり、不動産市場への重圧が懸念された。",
        "証券市場全体で5.4兆ドン超の巨額資金調達目標が設定された。"
      ]
    },
    {
      "title": "経済成長期待と新たな産業機会",
      "points": [
        "スタンチャー銀行が2026年GDP予測を9.5%に上方修正するなど、経済成長への期待は継続。",
        "中国がベトナム海産物の最大市場となり、輸出の堅調さが示唆された。",
        "ADBが質的成長への転換を提言し、炭素クレジットが新たな「金脈」として注目された。"
      ]
    },
    {
      "title": "地域経済の活性化と個別セクターの動き",
      "points": [
        "ゲアン省の上半期FDIが全国3位に急浮上し、地域経済の活性化が示された。",
        "シンガポール企業による屋上太陽光発電への13.9億円調達など、再生可能エネルギー分野での動きが見られた。",
        "フーコック党書記の新任により、同地域の開発加速への期待が高まった。"
      ]
    }
  ],
  "dramas": [
    "FPT（FPT）が31ヶ月ぶり安値を更新し、市場に動揺を与えた。",
    "PNJ（PNJ）がNguoi Ban Vangとの提携解消と全株式売却を発表した。",
    "ビングループ（VIC）がVHM株480万株超の譲渡を予定していることが報じられた。",
    "BSCがTCB（TCB）とHPG（HPG）に12.4億円超の投資を行った。",
    "HDバンク（HDB）がフィッチから初の格付けを取得した。"
  ]
}